okome/__init__.py
okome/py.typed
okome-0.0.1.dist-info/LICENSE
okome-0.0.1.dist-info/WHEEL
okome-0.0.1.dist-info/METADATA
okome-0.0.1.dist-info/RECORD
