Metadata-Version: 2.1
Name: okome
Version: 0.0.1
Summary: dataclass comment parser
License: MIT
Author: yukinarit
Author-email: yukinarit84@gmail.com
Requires-Python: >=3.6.1,<4.0.0
Classifier: License :: OSI Approved :: MIT License
Classifier: Programming Language :: Python :: 3
Classifier: Programming Language :: Python :: 3.7
Classifier: Programming Language :: Python :: 3.8
Classifier: Programming Language :: Python :: 3.9
Requires-Dist: dataclasses; python_version < "3.7"
